tinyagent/__init__.py
tinyagent/legacy_mcp_client.py
tinyagent/mcp_client.py
tinyagent/memory_manager.py
tinyagent/tiny_agent.py
tinyagent/code_agent/__init__.py
tinyagent/code_agent/example.py
tinyagent/code_agent/helper.py
tinyagent/code_agent/modal_sandbox.py
tinyagent/code_agent/safety.py
tinyagent/code_agent/shell_validator.py
tinyagent/code_agent/tiny_code_agent.py
tinyagent/code_agent/utils.py
tinyagent/code_agent/providers/__init__.py
tinyagent/code_agent/providers/base.py
tinyagent/code_agent/providers/bubblewrap_provider.py
tinyagent/code_agent/providers/docker_image_builder.py
tinyagent/code_agent/providers/docker_provider.py
tinyagent/code_agent/providers/modal_provider.py
tinyagent/code_agent/providers/seatbelt_provider.py
tinyagent/code_agent/tools/__init__.py
tinyagent/code_agent/tools/example_tools.py
tinyagent/code_agent/tools/file_tools.py
tinyagent/core/__init__.py
tinyagent/core/custom_instructions.py
tinyagent/core/openai_responses_adapter.py
tinyagent/hooks/__init__.py
tinyagent/hooks/anthropic_prompt_cache.py
tinyagent/hooks/gradio_callback.py
tinyagent/hooks/jupyter_notebook_callback.py
tinyagent/hooks/logging_manager.py
tinyagent/hooks/message_cleanup.py
tinyagent/hooks/rich_code_ui_callback.py
tinyagent/hooks/rich_ui_callback.py
tinyagent/hooks/token_tracker.py
tinyagent/prompts/code_agent.yaml
tinyagent/prompts/summarize.yaml
tinyagent/prompts/truncation.yaml
tinyagent/storage/__init__.py
tinyagent/storage/base.py
tinyagent/storage/json_file_storage.py
tinyagent/storage/postgres_storage.py
tinyagent/storage/redis_storage.py
tinyagent/storage/sqlite_storage.py
tinyagent/tools/__init__.py
tinyagent/tools/todo_write.py
tinyagent/tools/builders/__init__.py
tinyagent/tools/builders/analysis_subagent.py
tinyagent/tools/builders/coding_subagent.py
tinyagent/tools/builders/research_subagent.py
tinyagent/tools/subagent/__init__.py
tinyagent/tools/subagent/config.py
tinyagent/tools/subagent/context.py
tinyagent/tools/subagent/subagent_tool.py
tinyagent_py-0.1.20.dist-info/licenses/LICENSE
tinyagent_py-0.1.20.dist-info/METADATA
tinyagent_py-0.1.20.dist-info/WHEEL
tinyagent_py-0.1.20.dist-info/top_level.txt
tinyagent_py-0.1.20.dist-info/RECORD
