Metadata-Version: 2.4
Name: tinyagent-py
Version: 0.1.20
Summary: 🛠️ Build your own AI coding assistant with any model you want. Revolutionary agent framework with secure sandboxed execution, parallel subagents, and freedom to choose any LLM provider - OpenAI, Anthropic, Ollama, or 100+ others.
Author-email: Mahdi Golchin <golchin@askdev.ai>
Project-URL: Homepage, https://github.com/askbudi/tinyagent
Project-URL: Bug Tracker, https://github.com/askbudi/tinyagent/issues
Project-URL: Chat, https://askdev.ai/github/askbudi/tinyagent
Requires-Python: >=3.8
License-File: LICENSE
Requires-Dist: mcp
Requires-Dist: litellm
Requires-Dist: openai
Requires-Dist: tiktoken
Requires-Dist: uuid
Provides-Extra: dev
Requires-Dist: pytest; extra == "dev"
Requires-Dist: black; extra == "dev"
Requires-Dist: isort; extra == "dev"
Requires-Dist: mypy; extra == "dev"
Provides-Extra: postgres
Requires-Dist: asyncpg>=0.27.0; extra == "postgres"
Provides-Extra: sqlite
Requires-Dist: aiosqlite>=0.18.0; extra == "sqlite"
Provides-Extra: gradio
Requires-Dist: gradio>=3.50.0; extra == "gradio"
Provides-Extra: code
Requires-Dist: jinja2; extra == "code"
Requires-Dist: pyyaml; extra == "code"
Requires-Dist: cloudpickle; extra == "code"
Requires-Dist: modal; extra == "code"
Provides-Extra: all
Requires-Dist: asyncpg>=0.27.0; extra == "all"
Requires-Dist: aiosqlite>=0.18.0; extra == "all"
Requires-Dist: gradio>=3.50.0; extra == "all"
Requires-Dist: jinja2; extra == "all"
Requires-Dist: pyyaml; extra == "all"
Requires-Dist: cloudpickle; extra == "all"
Requires-Dist: modal; extra == "all"
Dynamic: license-file
